[
  {
    "id": "29534",
    "name": "Stark School",
    "address": {
      "address1": "10 Seed Street",
      "town": "London",
      "postcode": "N19 4PT"
    }
  },
  {
    "id": "11812",
    "name": "Ultron Academy",
    "address": {
      "address1": "10 Seed Street",
      "town": "London",
      "postcode": "N19 4PT"
    }
  },
  {
    "id": "98792",
    "name": "Thanos College",
    "address": {
      "address1": "10 Seed Street",
      "town": "London",
      "postcode": "N19 4PT"
    }
  }
]